ppy_jsonyml/__init__.py
ppy_jsonyml/converter/__init__.py
ppy_jsonyml/converter/od_base.py
ppy_jsonyml/converter/od_converter.py
ppy_jsonyml/converter/od_util.py
ppy_jsonyml/converter/yaml_converter.py
ppy_jsonyml/csv_sys/__init__.py
ppy_jsonyml/csv_sys/csv_processor.py
ppy_jsonyml/env/__init__.py
ppy_jsonyml/env/yaml_config_loader.py
ppy_jsonyml/env/yaml_config_obj.py
ppy_jsonyml/test/__init__.py
ppy_jsonyml/test/odc_test.py
ppy_jsonyml/util/__init__.py
ppy_jsonyml/util/json_util.py
ppy_jsonyml-0.0.7.dist-info/LICENSE
ppy_jsonyml-0.0.7.dist-info/METADATA
ppy_jsonyml-0.0.7.dist-info/WHEEL
ppy_jsonyml-0.0.7.dist-info/top_level.txt
ppy_jsonyml-0.0.7.dist-info/RECORD
