Metadata-Version: 2.1
Name: ppy-jsonyml
Version: 0.0.7
Summary: PWeb Python JSON & YAML is a library which help to serialize and deserialize Object as well as help to load configuration
Home-page: https://github.com/banglafighter/ppy-jsonyml
Author: Bangla Fighter
Author-email: problemfighter.com@gmail.com
License: Apache 2.0
Platform: any
Classifier: Intended Audience :: Developers
Classifier: License :: OSI Approved :: Apache Software License
Classifier: Programming Language :: Python
License-File: LICENSE
Requires-Dist: PyYAML ==6.0.1
Requires-Dist: ppy-common
Requires-Dist: ppy-file-text
